reposcorer/__init__.py
reposcorer/scorer.py
reposcorer/utility.py
reposcorer/attributes/__init__.py
reposcorer/attributes/comments.py
reposcorer/attributes/community.py
reposcorer/attributes/continuous_integration.py
reposcorer/attributes/history.py
reposcorer/attributes/iac.py
reposcorer/attributes/issues.py
reposcorer/attributes/licensing.py
reposcorer/attributes/loc_info.py
tests/attributes/__init__.py
tests/attributes/test_attributes.py
repository_scorer-0.5.1.dist-info/LICENSE
repository_scorer-0.5.1.dist-info/METADATA
repository_scorer-0.5.1.dist-info/WHEEL
repository_scorer-0.5.1.dist-info/top_level.txt
repository_scorer-0.5.1.dist-info/RECORD
